[{
	"Title": "9",
	"Year": "2009",
	"Rated": "PG-13",
	"Released": "09 Sep 2009",
	"Runtime": "79 min",
	"Genre": ["Animation", "Action", "Adventure", "Sci-Fi"],
	"Director": "Shane Acker",
	"Writer": "Pamela Pettler (screenplay by), Shane Acker (story by)",
	"Actors": "Christopher Plummer, Martin Landau, John C. Reilly, Crispin Glover",
	"Cast": [{
			"actor": "Christopher Plummer",
			"actor_id": "nm0001626",
			"character": "#1"
		},
		{
			"actor": "Martin Landau",
			"actor_id": "nm0001445",
			"character": "#2"
		},
		{
			"actor": "John C. Reilly",
			"actor_id": "nm0000604",
			"character": "#5"
		},
		{
			"actor": "Crispin Glover",
			"actor_id": "nm0000417",
			"character": "#6"
		},
		{
			"actor": "Jennifer Connelly",
			"actor_id": "nm0000124",
			"character": "#7"
		},
		{
			"actor": "Fred Tatasciore",
			"actor_id": "nm0851317",
			"character": "#8"
		},
		{
			"actor": "Elijah Wood",
			"actor_id": "nm0000704",
			"character": "#9"
		},
		{
			"actor": "Alan Oppenheimer",
			"actor_id": "nm0649178",
			"character": "Scientist"
		},
		{
			"actor": "Tom Kane",
			"actor_id": "nm0437454",
			"character": "Dictator (voice)"
		},
		{
			"actor": "Helen Wilson",
			"actor_id": "nm1409045",
			"character": "News Caster (voice)"
		}
	],
	"Plot": "A rag doll that awakens in a postapocalyptic future holds the key to humanity's salvation.",
	"Language": "English",
	"Country": "USA",
	"Awards": "9 nominations.",
	"Poster": "https://m.media-amazon.com/images/M/MV5BMTY2ODE1MTgxMV5BMl5BanBnXkFtZTcwNTM1NTM2Mg@@._V1_SX300.jpg",
	"Ratings": [{
			"Source": "Internet Movie Database",
			"Value": "7.1/10"
		},
		{
			"Source": "Rotten Tomatoes",
			"Value": "57%"
		},
		{
			"Source": "Metacritic",
			"Value": "60/100"
		}
	],
	"Metascore": "60",
	"imdbRating": "7.1",
	"imdbVotes": "133,108",
	"imdbID": "tt0472033",
	"Type": "movie",
	"DVD": "N/A",
	"BoxOffice": "$31,749,894",
	"Production": "Jim Lemley, Timur Bekmambetov, Tim Burton Animation Co.",
	"Website": "N/A",
	"Response": "True"
}]
